yfinance/__init__.py
yfinance/base.py
yfinance/cache.py
yfinance/const.py
yfinance/data.py
yfinance/exceptions.py
yfinance/multi.py
yfinance/shared.py
yfinance/ticker.py
yfinance/tickers.py
yfinance/utils.py
yfinance/version.py
yfinance/scrapers/__init__.py
yfinance/scrapers/analysis.py
yfinance/scrapers/fundamentals.py
yfinance/scrapers/holders.py
yfinance/scrapers/quote.py
zyfinance-0.2.33.dist-info/LICENSE.txt
zyfinance-0.2.33.dist-info/METADATA
zyfinance-0.2.33.dist-info/WHEEL
zyfinance-0.2.33.dist-info/entry_points.txt
zyfinance-0.2.33.dist-info/top_level.txt
zyfinance-0.2.33.dist-info/RECORD
